pygroupme/__init__.py
pygroupme-0.0.3.dist-info/METADATA
pygroupme-0.0.3.dist-info/WHEEL
pygroupme-0.0.3.dist-info/top_level.txt
pygroupme-0.0.3.dist-info/RECORD
