Metadata-Version: 2.1
Name: pygroupme
Version: 0.0.3
Summary: Easy use of the GroupMe API with Python
Home-page: https://github.com/rudiejd/pygroupme
Author: JD Rudie
Author-email: rudiejd@miamioh.edu
License: UNKNOWN
Platform: UNKNOWN
Classifier: Programming Language :: Python :: 3
Classifier: License :: OSI Approved :: MIT License
Classifier: Operating System :: OS Independent
Requires-Dist: requests
